<template>
    <sequence>
        <line length="4" isStart="true" middleLine="solid-dashed" />
        <line length="1" />
        <intersection turn="left" rule="stop" length_east_side="3.21" length_north_side="4.65" />
        <line length="2" />
        <intersection turn="straight" rule="priority-yield" length_west_side="6" length_east_side="5.32" />
        <line length="0.2" middleLine="missing" />
        <intersection turn="straight" rule="yield" length_west_side="2.2" length_east_side="2.75" />
        <intersection turn="straight" rule="stop" length_west_side="3" length_east_side="3" />
        <line length="2" />
        <intersection turn="straight" rule="equal" length_west_side="3.5" length_east_side="5.15" />
        <line length="1.75" />
        <intersection turn="straight" rule="priority-stop" length_west_side="4" length_east_side="4" />
        <line length="2" />
        <intersection turn="left" rule="yield" length_east_side="2.1" length_north_side="1.35" />
        <line length="1" />
        <intersection turn="straight" rule="equal" length_west_side="2" length_east_side="1.8" />
        <line length="1.34" />
        <intersection turn="straight" rule="stop" length_west_side="2.4" length_east_side="2.64" />
        <line length="2" />
        <intersection turn="left" rule="priority-kinked-left" length_west_side="0.9" length_north_side="4.6" />
        <line length="1" />
        <line length="1" middleLine="solid-dashed" />
        <leftArc radius="2" angle="90" middleLine="solid-dashed" />
        <rightArc radius="3" angle="90.1" middleLine="solid-dashed" />
        <line length="0.01" middleLine="solid-dashed" />
        <line length="1.98" />
        <trafficSign type="stvo-276" />
        <rightArc radius="2" angle="90" middleLine="double-solid" />
        <leftArc radius="3" angle="90.1" middleLine="double-solid" />
        <line length="0.01" middleLine="double-solid" />
        <line length="2.738" />
        <intersection turn="left" rule="stop" length_west_side="3.5" length_north_side="1.5" />
        <line length="0.34" />
    </sequence>
</template>